[{"year":1986.0,"manufacturer":"mazda","model":"b2000","url":"https:\/\/skagit.craigslist.org\/cto\/d\/north-lakewood-1986-mazda-b-speed\/7046156663.html","price":1250,"condition":"fair","odometer":307000.0,"state":"wa","lat":48.1829,"long":-122.112},{"year":2002.0,"manufacturer":"mazda","model":"b3000","url":"https:\/\/anchorage.craigslist.org\/cto\/d\/anchorage-2002-mazda-b3000-cab-plus\/7039535135.html","price":3000,"condition":"good","odometer":142906.0,"state":"ak","lat":61.2037,"long":-149.745},{"year":1996.0,"manufacturer":"mazda","model":"b4000","url":"https:\/\/susanville.craigslist.org\/cto\/d\/standish-1996-mazda-b4000-4x4-cab\/7042969793.html","price":3950,"condition":"good","odometer":245000.0,"state":"ca","lat":40.3509,"long":-120.407},{"year":1993.0,"manufacturer":"mazda","model":"b2600","url":"https:\/\/westslope.craigslist.org\/cto\/d\/parachute-pristine-93-mazda-pu-4x4-cab\/7040910228.html","price":2950,"condition":"excellent","odometer":196900.0,"state":"co","lat":39.5199,"long":-108.048},{"year":2002.0,"manufacturer":"mazda","model":"b3000 dual sport","url":"https:\/\/jacksonville.craigslist.org\/cto\/d\/vero-beach-2002-mazda-b3000-dual-sport\/7044125504.html","price":4995,"condition":"excellent","odometer":122276.0,"state":"fl","lat":27.633,"long":-80.4031},{"year":1998.0,"manufacturer":"mazda","model":"b3000","url":"https:\/\/lakeland.craigslist.org\/cto\/d\/dearing-mazda-b3000-se-v6-low-miles\/7033181587.html","price":5000,"condition":"like new","odometer":71982.0,"state":"fl","lat":37.1328,"long":-95.7856},{"year":2002.0,"manufacturer":"mazda","model":"b3000 dual sport","url":"https:\/\/treasure.craigslist.org\/cto\/d\/vero-beach-2002-mazda-b-owner-very-low\/7041060997.html","price":4995,"condition":"like new","odometer":122276.0,"state":"fl","lat":27.633,"long":-80.4031},{"year":1994.0,"manufacturer":"mazda","model":"se5","url":"https:\/\/macon.craigslist.org\/cto\/d\/milledgeville-94-mazda-se5\/7047055494.html","price":2500,"condition":"good","odometer":181837.0,"state":"ga","lat":33.08,"long":-83.2379},{"year":1997.0,"manufacturer":"mazda","model":"b2300","url":"https:\/\/savannah.craigslist.org\/cto\/d\/savannah-1997-mazda-b2300-u\/7032696874.html","price":3200,"condition":"good","odometer":160000.0,"state":"ga","lat":32.1419,"long":-81.1631},{"year":2002.0,"manufacturer":"mazda","model":"b3000","url":"https:\/\/wichita.craigslist.org\/cto\/d\/wichita-2002-mazda-b3000\/7049668972.html","price":4250,"condition":"good","odometer":147000.0,"state":"ks","lat":37.7639,"long":-97.4269},{"year":1997.0,"manufacturer":"mazda","model":"b2300","url":"https:\/\/louisville.craigslist.org\/cto\/d\/louisville-mazda-pick-up-truck\/7047246131.html","price":2500,"condition":"excellent","odometer":164000.0,"state":"ky","lat":38.1381,"long":-85.6953},{"year":2002.0,"manufacturer":"mazda","model":"b3000 dual sport","url":"https:\/\/neworleans.craigslist.org\/cto\/d\/new-orleans-2002-mazda-b3000\/7033615394.html","price":2500,"condition":"good","odometer":199900.0,"state":"la","lat":29.9687,"long":-90.0473},{"year":1989.0,"manufacturer":"mazda","model":"b2600i","url":"https:\/\/greatfalls.craigslist.org\/cto\/d\/great-falls-mazda-pickup\/7042712039.html","price":2000,"condition":"good","odometer":97000.0,"state":"mt","lat":47.5098,"long":-111.34},{"year":2002.0,"manufacturer":"mazda","model":"b4000","url":"https:\/\/missoula.craigslist.org\/cto\/d\/missoula-mazda-truck\/7040389167.html","price":4500,"condition":"good","odometer":182460.0,"state":"mt","lat":46.8772,"long":-114.038},{"year":2006.0,"manufacturer":"mazda","model":"b3000 dual sport","url":"https:\/\/eastnc.craigslist.org\/cto\/d\/virginia-beach-2006-mazda-b3000-dual\/7045339794.html","price":3200,"condition":"good","odometer":214000.0,"state":"nc","lat":36.7341,"long":-76.0359},{"year":1984.0,"manufacturer":"mazda","model":"b2000","url":"https:\/\/santafe.craigslist.org\/cto\/d\/santa-fe-84-mazda-b2000-long-bed\/7048707572.html","price":3750,"condition":"like new","odometer":106000.0,"state":"nm","lat":35.5946,"long":-106.043},{"year":2003.0,"manufacturer":"mazda","model":"b3000","url":"https:\/\/cleveland.craigslist.org\/cto\/d\/cleveland-2003-mazda-b3000-includes\/7042885226.html","price":1700,"condition":"good","odometer":135000.0,"state":"oh","lat":41.4888,"long":-81.7687},{"year":2001.0,"manufacturer":"mazda","model":"b3000","url":"https:\/\/portland.craigslist.org\/clk\/ctd\/d\/cornelius-2001-mazda-b3000-4wd-stock\/7049793241.html","price":7995,"condition":"excellent","odometer":91258.0,"state":"or","lat":45.52,"long":-123.037},{"year":1994.0,"manufacturer":"mazda","model":"b2300","url":"https:\/\/salem.craigslist.org\/ctd\/d\/independence-1994-mazda-b2300low-down\/7049315490.html","price":1795,"condition":"good","odometer":218000.0,"state":"or","lat":44.8486,"long":-123.188},{"year":2003.0,"manufacturer":"mazda","model":"b2300","url":"https:\/\/waco.craigslist.org\/cto\/d\/waco-2003-mazda-b2300\/7038464138.html","price":3000,"condition":"good","odometer":141653.0,"state":"tx","lat":31.5765,"long":-97.1786}]